{
  "0000": {
    "postcode": "3740000",
    "prefecture": "群馬県",
    "prefecture_kana": "グンマケン",
    "prefecture_code": 10,
    "city": "館林市",
    "city_kana": "タテバヤシシ",
    "town": "",
    "town_kana": "",
    "street": null,
    "office_name": null,
    "office_name_kana": null
  },
  "0001": {
    "postcode": "3740001",
    "prefecture": "群馬県",
    "prefecture_kana": "グンマケン",
    "prefecture_code": 10,
    "city": "館林市",
    "city_kana": "タテバヤシシ",
    "town": "大島町",
    "town_kana": "オオシマチョウ",
    "street": null,
    "office_name": null,
    "office_name_kana": null
  },
  "0002": {
    "postcode": "3740002",
    "prefecture": "群馬県",
    "prefecture_kana": "グンマケン",
    "prefecture_code": 10,
    "city": "館林市",
    "city_kana": "タテバヤシシ",
    "town": "田谷町",
    "town_kana": "タヤチョウ",
    "street": null,
    "office_name": null,
    "office_name_kana": null
  },
  "0003": {
    "postcode": "3740003",
    "prefecture": "群馬県",
    "prefecture_kana": "グンマケン",
    "prefecture_code": 10,
    "city": "館林市",
    "city_kana": "タテバヤシシ",
    "town": "四ツ谷町",
    "town_kana": "ヨツヤチョウ",
    "street": null,
    "office_name": null,
    "office_name_kana": null
  },
  "0004": {
    "postcode": "3740004",
    "prefecture": "群馬県",
    "prefecture_kana": "グンマケン",
    "prefecture_code": 10,
    "city": "館林市",
    "city_kana": "タテバヤシシ",
    "town": "楠町",
    "town_kana": "クスノキチョウ",
    "street": null,
    "office_name": null,
    "office_name_kana": null
  },
  "0005": {
    "postcode": "3740005",
    "prefecture": "群馬県",
    "prefecture_kana": "グンマケン",
    "prefecture_code": 10,
    "city": "館林市",
    "city_kana": "タテバヤシシ",
    "town": "花山町",
    "town_kana": "ハナヤマチョウ",
    "street": null,
    "office_name": null,
    "office_name_kana": null
  },
  "0006": {
    "postcode": "3740006",
    "prefecture": "群馬県",
    "prefecture_kana": "グンマケン",
    "prefecture_code": 10,
    "city": "館林市",
    "city_kana": "タテバヤシシ",
    "town": "当郷町",
    "town_kana": "トウゴウチョウ",
    "street": null,
    "office_name": null,
    "office_name_kana": null
  },
  "0007": {
    "postcode": "3740007",
    "prefecture": "群馬県",
    "prefecture_kana": "グンマケン",
    "prefecture_code": 10,
    "city": "館林市",
    "city_kana": "タテバヤシシ",
    "town": "若宮町",
    "town_kana": "ワカミヤチョウ",
    "street": null,
    "office_name": null,
    "office_name_kana": null
  },
  "0008": {
    "postcode": "3740008",
    "prefecture": "群馬県",
    "prefecture_kana": "グンマケン",
    "prefecture_code": 10,
    "city": "館林市",
    "city_kana": "タテバヤシシ",
    "town": "細内町",
    "town_kana": "ホソウチチョウ",
    "street": null,
    "office_name": null,
    "office_name_kana": null
  },
  "0009": {
    "postcode": "3740009",
    "prefecture": "群馬県",
    "prefecture_kana": "グンマケン",
    "prefecture_code": 10,
    "city": "館林市",
    "city_kana": "タテバヤシシ",
    "town": "千塚町",
    "town_kana": "チヅカチョウ",
    "street": null,
    "office_name": null,
    "office_name_kana": null
  },
  "0011": {
    "postcode": "3740011",
    "prefecture": "群馬県",
    "prefecture_kana": "グンマケン",
    "prefecture_code": 10,
    "city": "館林市",
    "city_kana": "タテバヤシシ",
    "town": "羽附町",
    "town_kana": "ハネツクチョウ",
    "street": null,
    "office_name": null,
    "office_name_kana": null
  },
  "0012": {
    "postcode": "3740012",
    "prefecture": "群馬県",
    "prefecture_kana": "グンマケン",
    "prefecture_code": 10,
    "city": "館林市",
    "city_kana": "タテバヤシシ",
    "town": "羽附旭町",
    "town_kana": "ハネツクアサヒチョウ",
    "street": null,
    "office_name": null,
    "office_name_kana": null
  },
  "0013": {
    "postcode": "3740013",
    "prefecture": "群馬県",
    "prefecture_kana": "グンマケン",
    "prefecture_code": 10,
    "city": "館林市",
    "city_kana": "タテバヤシシ",
    "town": "赤生田町",
    "town_kana": "アコウダチョウ",
    "street": null,
    "office_name": null,
    "office_name_kana": null
  },
  "0014": {
    "postcode": "3740014",
    "prefecture": "群馬県",
    "prefecture_kana": "グンマケン",
    "prefecture_code": 10,
    "city": "館林市",
    "city_kana": "タテバヤシシ",
    "town": "赤生田本町",
    "town_kana": "アコウダホンチョウ",
    "street": null,
    "office_name": null,
    "office_name_kana": null
  },
  "0015": {
    "postcode": "3740015",
    "prefecture": "群馬県",
    "prefecture_kana": "グンマケン",
    "prefecture_code": 10,
    "city": "館林市",
    "city_kana": "タテバヤシシ",
    "town": "上赤生田町",
    "town_kana": "カミアコウダチョウ",
    "street": null,
    "office_name": null,
    "office_name_kana": null
  },
  "0016": {
    "postcode": "3740016",
    "prefecture": "群馬県",
    "prefecture_kana": "グンマケン",
    "prefecture_code": 10,
    "city": "館林市",
    "city_kana": "タテバヤシシ",
    "town": "松原",
    "town_kana": "マツバラ",
    "street": null,
    "office_name": null,
    "office_name_kana": null
  },
  "0017": {
    "postcode": "3740017",
    "prefecture": "群馬県",
    "prefecture_kana": "グンマケン",
    "prefecture_code": 10,
    "city": "館林市",
    "city_kana": "タテバヤシシ",
    "town": "つつじ町",
    "town_kana": "ツツジチョウ",
    "street": null,
    "office_name": null,
    "office_name_kana": null
  },
  "0018": {
    "postcode": "3740018",
    "prefecture": "群馬県",
    "prefecture_kana": "グンマケン",
    "prefecture_code": 10,
    "city": "館林市",
    "city_kana": "タテバヤシシ",
    "town": "城町",
    "town_kana": "シロマチ",
    "street": null,
    "office_name": null,
    "office_name_kana": null
  },
  "0019": {
    "postcode": "3740019",
    "prefecture": "群馬県",
    "prefecture_kana": "グンマケン",
    "prefecture_code": 10,
    "city": "館林市",
    "city_kana": "タテバヤシシ",
    "town": "尾曳町",
    "town_kana": "オビキチョウ",
    "street": null,
    "office_name": null,
    "office_name_kana": null
  },
  "0021": {
    "postcode": "3740021",
    "prefecture": "群馬県",
    "prefecture_kana": "グンマケン",
    "prefecture_code": 10,
    "city": "館林市",
    "city_kana": "タテバヤシシ",
    "town": "瀬戸谷町",
    "town_kana": "セドヤチョウ",
    "street": null,
    "office_name": null,
    "office_name_kana": null
  },
  "0022": {
    "postcode": "3740022",
    "prefecture": "群馬県",
    "prefecture_kana": "グンマケン",
    "prefecture_code": 10,
    "city": "館林市",
    "city_kana": "タテバヤシシ",
    "town": "加法師町",
    "town_kana": "カボウシチョウ",
    "street": null,
    "office_name": null,
    "office_name_kana": null
  },
  "0023": {
    "postcode": "3740023",
    "prefecture": "群馬県",
    "prefecture_kana": "グンマケン",
    "prefecture_code": 10,
    "city": "館林市",
    "city_kana": "タテバヤシシ",
    "town": "大手町",
    "town_kana": "オオテマチ",
    "street": null,
    "office_name": null,
    "office_name_kana": null
  },
  "0024": {
    "postcode": "3740024",
    "prefecture": "群馬県",
    "prefecture_kana": "グンマケン",
    "prefecture_code": 10,
    "city": "館林市",
    "city_kana": "タテバヤシシ",
    "town": "本町",
    "town_kana": "ホンチョウ",
    "street": null,
    "office_name": null,
    "office_name_kana": null
  },
  "0025": {
    "postcode": "3740025",
    "prefecture": "群馬県",
    "prefecture_kana": "グンマケン",
    "prefecture_code": 10,
    "city": "館林市",
    "city_kana": "タテバヤシシ",
    "town": "緑町",
    "town_kana": "ミドリチョウ",
    "street": null,
    "office_name": null,
    "office_name_kana": null
  },
  "0026": {
    "postcode": "3740026",
    "prefecture": "群馬県",
    "prefecture_kana": "グンマケン",
    "prefecture_code": 10,
    "city": "館林市",
    "city_kana": "タテバヤシシ",
    "town": "新宿",
    "town_kana": "シンジュク",
    "street": null,
    "office_name": null,
    "office_name_kana": null
  },
  "0027": {
    "postcode": "3740027",
    "prefecture": "群馬県",
    "prefecture_kana": "グンマケン",
    "prefecture_code": 10,
    "city": "館林市",
    "city_kana": "タテバヤシシ",
    "town": "富士見町",
    "town_kana": "フジミチョウ",
    "street": null,
    "office_name": null,
    "office_name_kana": null
  },
  "0028": {
    "postcode": "3740028",
    "prefecture": "群馬県",
    "prefecture_kana": "グンマケン",
    "prefecture_code": 10,
    "city": "館林市",
    "city_kana": "タテバヤシシ",
    "town": "千代田町",
    "town_kana": "チヨダチョウ",
    "street": null,
    "office_name": null,
    "office_name_kana": null
  },
  "0029": {
    "postcode": "3740029",
    "prefecture": "群馬県",
    "prefecture_kana": "グンマケン",
    "prefecture_code": 10,
    "city": "館林市",
    "city_kana": "タテバヤシシ",
    "town": "仲町",
    "town_kana": "ナカマチ",
    "street": null,
    "office_name": null,
    "office_name_kana": null
  },
  "0031": {
    "postcode": "3740031",
    "prefecture": "群馬県",
    "prefecture_kana": "グンマケン",
    "prefecture_code": 10,
    "city": "館林市",
    "city_kana": "タテバヤシシ",
    "town": "東美園町",
    "town_kana": "ヒガシミソノチョウ",
    "street": null,
    "office_name": null,
    "office_name_kana": null
  },
  "0032": {
    "postcode": "3740032",
    "prefecture": "群馬県",
    "prefecture_kana": "グンマケン",
    "prefecture_code": 10,
    "city": "館林市",
    "city_kana": "タテバヤシシ",
    "town": "南美園町",
    "town_kana": "ミナミミソノチョウ",
    "street": null,
    "office_name": null,
    "office_name_kana": null
  },
  "0033": {
    "postcode": "3740033",
    "prefecture": "群馬県",
    "prefecture_kana": "グンマケン",
    "prefecture_code": 10,
    "city": "館林市",
    "city_kana": "タテバヤシシ",
    "town": "堀工町",
    "town_kana": "ホリクチョウ",
    "street": null,
    "office_name": null,
    "office_name_kana": null
  },
  "0034": {
    "postcode": "3740034",
    "prefecture": "群馬県",
    "prefecture_kana": "グンマケン",
    "prefecture_code": 10,
    "city": "館林市",
    "city_kana": "タテバヤシシ",
    "town": "分福町",
    "town_kana": "ブンブクチョウ",
    "street": null,
    "office_name": null,
    "office_name_kana": null
  },
  "0035": {
    "postcode": "3740035",
    "prefecture": "群馬県",
    "prefecture_kana": "グンマケン",
    "prefecture_code": 10,
    "city": "館林市",
    "city_kana": "タテバヤシシ",
    "town": "青柳町",
    "town_kana": "アオヤギチョウ",
    "street": null,
    "office_name": null,
    "office_name_kana": null
  },
  "0036": {
    "postcode": "3740036",
    "prefecture": "群馬県",
    "prefecture_kana": "グンマケン",
    "prefecture_code": 10,
    "city": "館林市",
    "city_kana": "タテバヤシシ",
    "town": "諏訪町",
    "town_kana": "スワチョウ",
    "street": null,
    "office_name": null,
    "office_name_kana": null
  },
  "0037": {
    "postcode": "3740037",
    "prefecture": "群馬県",
    "prefecture_kana": "グンマケン",
    "prefecture_code": 10,
    "city": "館林市",
    "city_kana": "タテバヤシシ",
    "town": "小桑原町",
    "town_kana": "コクワバラチョウ",
    "street": null,
    "office_name": null,
    "office_name_kana": null
  },
  "0038": {
    "postcode": "3740038",
    "prefecture": "群馬県",
    "prefecture_kana": "グンマケン",
    "prefecture_code": 10,
    "city": "館林市",
    "city_kana": "タテバヤシシ",
    "town": "西美園町",
    "town_kana": "ニシミソノチョウ",
    "street": null,
    "office_name": null,
    "office_name_kana": null
  },
  "0039": {
    "postcode": "3740039",
    "prefecture": "群馬県",
    "prefecture_kana": "グンマケン",
    "prefecture_code": 10,
    "city": "館林市",
    "city_kana": "タテバヤシシ",
    "town": "美園町",
    "town_kana": "ミソノチョウ",
    "street": null,
    "office_name": null,
    "office_name_kana": null
  },
  "0041": {
    "postcode": "3740041",
    "prefecture": "群馬県",
    "prefecture_kana": "グンマケン",
    "prefecture_code": 10,
    "city": "館林市",
    "city_kana": "タテバヤシシ",
    "town": "富士原町",
    "town_kana": "フジハラチョウ",
    "street": null,
    "office_name": null,
    "office_name_kana": null
  },
  "0042": {
    "postcode": "3740042",
    "prefecture": "群馬県",
    "prefecture_kana": "グンマケン",
    "prefecture_code": 10,
    "city": "館林市",
    "city_kana": "タテバヤシシ",
    "town": "近藤町",
    "town_kana": "コンドウチョウ",
    "street": null,
    "office_name": null,
    "office_name_kana": null
  },
  "0043": {
    "postcode": "3740043",
    "prefecture": "群馬県",
    "prefecture_kana": "グンマケン",
    "prefecture_code": 10,
    "city": "館林市",
    "city_kana": "タテバヤシシ",
    "town": "苗木町",
    "town_kana": "ナエギチョウ",
    "street": null,
    "office_name": null,
    "office_name_kana": null
  },
  "0044": {
    "postcode": "3740044",
    "prefecture": "群馬県",
    "prefecture_kana": "グンマケン",
    "prefecture_code": 10,
    "city": "館林市",
    "city_kana": "タテバヤシシ",
    "town": "下三林町",
    "town_kana": "シモミバヤシチョウ",
    "street": null,
    "office_name": null,
    "office_name_kana": null
  },
  "0045": {
    "postcode": "3740045",
    "prefecture": "群馬県",
    "prefecture_kana": "グンマケン",
    "prefecture_code": 10,
    "city": "館林市",
    "city_kana": "タテバヤシシ",
    "town": "入ケ谷町",
    "town_kana": "イリカヤチョウ",
    "street": null,
    "office_name": null,
    "office_name_kana": null
  },
  "0046": {
    "postcode": "3740046",
    "prefecture": "群馬県",
    "prefecture_kana": "グンマケン",
    "prefecture_code": 10,
    "city": "館林市",
    "city_kana": "タテバヤシシ",
    "town": "上三林町",
    "town_kana": "カミミバヤシチョウ",
    "street": null,
    "office_name": null,
    "office_name_kana": null
  },
  "0047": {
    "postcode": "3740047",
    "prefecture": "群馬県",
    "prefecture_kana": "グンマケン",
    "prefecture_code": 10,
    "city": "館林市",
    "city_kana": "タテバヤシシ",
    "town": "野辺町",
    "town_kana": "ノベチョウ",
    "street": null,
    "office_name": null,
    "office_name_kana": null
  },
  "0051": {
    "postcode": "3740051",
    "prefecture": "群馬県",
    "prefecture_kana": "グンマケン",
    "prefecture_code": 10,
    "city": "館林市",
    "city_kana": "タテバヤシシ",
    "town": "新栄町",
    "town_kana": "シンサカエチョウ",
    "street": null,
    "office_name": null,
    "office_name_kana": null
  },
  "0052": {
    "postcode": "3740052",
    "prefecture": "群馬県",
    "prefecture_kana": "グンマケン",
    "prefecture_code": 10,
    "city": "館林市",
    "city_kana": "タテバヤシシ",
    "town": "栄町",
    "town_kana": "サカエチョウ",
    "street": null,
    "office_name": null,
    "office_name_kana": null
  },
  "0053": {
    "postcode": "3740053",
    "prefecture": "群馬県",
    "prefecture_kana": "グンマケン",
    "prefecture_code": 10,
    "city": "館林市",
    "city_kana": "タテバヤシシ",
    "town": "赤土町",
    "town_kana": "アカツチチョウ",
    "street": null,
    "office_name": null,
    "office_name_kana": null
  },
  "0054": {
    "postcode": "3740054",
    "prefecture": "群馬県",
    "prefecture_kana": "グンマケン",
    "prefecture_code": 10,
    "city": "館林市",
    "city_kana": "タテバヤシシ",
    "town": "大谷町",
    "town_kana": "オオヤチョウ",
    "street": null,
    "office_name": null,
    "office_name_kana": null
  },
  "0055": {
    "postcode": "3740055",
    "prefecture": "群馬県",
    "prefecture_kana": "グンマケン",
    "prefecture_code": 10,
    "city": "館林市",
    "city_kana": "タテバヤシシ",
    "town": "成島町",
    "town_kana": "ナルシマチョウ",
    "street": null,
    "office_name": null,
    "office_name_kana": null
  },
  "0056": {
    "postcode": "3740056",
    "prefecture": "群馬県",
    "prefecture_kana": "グンマケン",
    "prefecture_code": 10,
    "city": "館林市",
    "city_kana": "タテバヤシシ",
    "town": "松沼町",
    "town_kana": "マツヌマチョウ",
    "street": null,
    "office_name": null,
    "office_name_kana": null
  },
  "0057": {
    "postcode": "3740057",
    "prefecture": "群馬県",
    "prefecture_kana": "グンマケン",
    "prefecture_code": 10,
    "city": "館林市",
    "city_kana": "タテバヤシシ",
    "town": "北成島町",
    "town_kana": "キタナルシマチョウ",
    "street": null,
    "office_name": null,
    "office_name_kana": null
  },
  "0061": {
    "postcode": "3740061",
    "prefecture": "群馬県",
    "prefecture_kana": "グンマケン",
    "prefecture_code": 10,
    "city": "館林市",
    "city_kana": "タテバヤシシ",
    "town": "東広内町",
    "town_kana": "ヒガシヒロウチチョウ",
    "street": null,
    "office_name": null,
    "office_name_kana": null
  },
  "0062": {
    "postcode": "3740062",
    "prefecture": "群馬県",
    "prefecture_kana": "グンマケン",
    "prefecture_code": 10,
    "city": "館林市",
    "city_kana": "タテバヤシシ",
    "town": "広内町",
    "town_kana": "ヒロウチチョウ",
    "street": null,
    "office_name": null,
    "office_name_kana": null
  },
  "0063": {
    "postcode": "3740063",
    "prefecture": "群馬県",
    "prefecture_kana": "グンマケン",
    "prefecture_code": 10,
    "city": "館林市",
    "city_kana": "タテバヤシシ",
    "town": "朝日町",
    "town_kana": "アサヒチョウ",
    "street": null,
    "office_name": null,
    "office_name_kana": null
  },
  "0064": {
    "postcode": "3740064",
    "prefecture": "群馬県",
    "prefecture_kana": "グンマケン",
    "prefecture_code": 10,
    "city": "館林市",
    "city_kana": "タテバヤシシ",
    "town": "代官町",
    "town_kana": "ダイカンチョウ",
    "street": null,
    "office_name": null,
    "office_name_kana": null
  },
  "0065": {
    "postcode": "3740065",
    "prefecture": "群馬県",
    "prefecture_kana": "グンマケン",
    "prefecture_code": 10,
    "city": "館林市",
    "city_kana": "タテバヤシシ",
    "town": "西本町",
    "town_kana": "ニシホンチョウ",
    "street": null,
    "office_name": null,
    "office_name_kana": null
  },
  "0066": {
    "postcode": "3740066",
    "prefecture": "群馬県",
    "prefecture_kana": "グンマケン",
    "prefecture_code": 10,
    "city": "館林市",
    "city_kana": "タテバヤシシ",
    "town": "大街道",
    "town_kana": "オオカイドウ",
    "street": null,
    "office_name": null,
    "office_name_kana": null
  },
  "0067": {
    "postcode": "3740067",
    "prefecture": "群馬県",
    "prefecture_kana": "グンマケン",
    "prefecture_code": 10,
    "city": "館林市",
    "city_kana": "タテバヤシシ",
    "town": "岡野町",
    "town_kana": "オカノチョウ",
    "street": null,
    "office_name": null,
    "office_name_kana": null
  },
  "0068": {
    "postcode": "3740068",
    "prefecture": "群馬県",
    "prefecture_kana": "グンマケン",
    "prefecture_code": 10,
    "city": "館林市",
    "city_kana": "タテバヤシシ",
    "town": "台宿町",
    "town_kana": "ダイジュクチョウ",
    "street": null,
    "office_name": null,
    "office_name_kana": null
  },
  "0069": {
    "postcode": "3740069",
    "prefecture": "群馬県",
    "prefecture_kana": "グンマケン",
    "prefecture_code": 10,
    "city": "館林市",
    "city_kana": "タテバヤシシ",
    "town": "坂下町",
    "town_kana": "サカシタチョウ",
    "street": null,
    "office_name": null,
    "office_name_kana": null
  },
  "0071": {
    "postcode": "3740071",
    "prefecture": "群馬県",
    "prefecture_kana": "グンマケン",
    "prefecture_code": 10,
    "city": "館林市",
    "city_kana": "タテバヤシシ",
    "town": "下早川田町",
    "town_kana": "シモサガワダチョウ",
    "street": null,
    "office_name": null,
    "office_name_kana": null
  },
  "0072": {
    "postcode": "3740072",
    "prefecture": "群馬県",
    "prefecture_kana": "グンマケン",
    "prefecture_code": 10,
    "city": "館林市",
    "city_kana": "タテバヤシシ",
    "town": "大新田町",
    "town_kana": "オオシンデンチョウ",
    "street": null,
    "office_name": null,
    "office_name_kana": null
  },
  "0073": {
    "postcode": "3740073",
    "prefecture": "群馬県",
    "prefecture_kana": "グンマケン",
    "prefecture_code": 10,
    "city": "館林市",
    "city_kana": "タテバヤシシ",
    "town": "足次町",
    "town_kana": "アシツギチョウ",
    "street": null,
    "office_name": null,
    "office_name_kana": null
  },
  "0074": {
    "postcode": "3740074",
    "prefecture": "群馬県",
    "prefecture_kana": "グンマケン",
    "prefecture_code": 10,
    "city": "館林市",
    "city_kana": "タテバヤシシ",
    "town": "高根町",
    "town_kana": "タカネチョウ",
    "street": null,
    "office_name": null,
    "office_name_kana": null
  },
  "0075": {
    "postcode": "3740075",
    "prefecture": "群馬県",
    "prefecture_kana": "グンマケン",
    "prefecture_code": 10,
    "city": "館林市",
    "city_kana": "タテバヤシシ",
    "town": "西高根町",
    "town_kana": "ニシタカネチョウ",
    "street": null,
    "office_name": null,
    "office_name_kana": null
  },
  "0076": {
    "postcode": "3740076",
    "prefecture": "群馬県",
    "prefecture_kana": "グンマケン",
    "prefecture_code": 10,
    "city": "館林市",
    "city_kana": "タテバヤシシ",
    "town": "日向町",
    "town_kana": "ヒナタチョウ",
    "street": null,
    "office_name": null,
    "office_name_kana": null
  },
  "0077": {
    "postcode": "3740077",
    "prefecture": "群馬県",
    "prefecture_kana": "グンマケン",
    "prefecture_code": 10,
    "city": "館林市",
    "city_kana": "タテバヤシシ",
    "town": "木戸町",
    "town_kana": "キドチョウ",
    "street": null,
    "office_name": null,
    "office_name_kana": null
  },
  "0078": {
    "postcode": "3740078",
    "prefecture": "群馬県",
    "prefecture_kana": "グンマケン",
    "prefecture_code": 10,
    "city": "館林市",
    "city_kana": "タテバヤシシ",
    "town": "傍示塚町",
    "town_kana": "ホウジツカチョウ",
    "street": null,
    "office_name": null,
    "office_name_kana": null
  },
  "0079": {
    "postcode": "3740079",
    "prefecture": "群馬県",
    "prefecture_kana": "グンマケン",
    "prefecture_code": 10,
    "city": "館林市",
    "city_kana": "タテバヤシシ",
    "town": "上早川田町",
    "town_kana": "カミサガワダチョウ",
    "street": null,
    "office_name": null,
    "office_name_kana": null
  },
  "0100": {
    "postcode": "3740100",
    "prefecture": "群馬県",
    "prefecture_kana": "グンマケン",
    "prefecture_code": 10,
    "city": "邑楽郡板倉町",
    "city_kana": "オウラグンイタクラマチ",
    "town": "",
    "town_kana": "",
    "street": null,
    "office_name": null,
    "office_name_kana": null
  },
  "0101": {
    "postcode": "3740101",
    "prefecture": "群馬県",
    "prefecture_kana": "グンマケン",
    "prefecture_code": 10,
    "city": "邑楽郡板倉町",
    "city_kana": "オウラグンイタクラマチ",
    "town": "除川",
    "town_kana": "ヨケガワ",
    "street": null,
    "office_name": null,
    "office_name_kana": null
  },
  "0102": {
    "postcode": "3740102",
    "prefecture": "群馬県",
    "prefecture_kana": "グンマケン",
    "prefecture_code": 10,
    "city": "邑楽郡板倉町",
    "city_kana": "オウラグンイタクラマチ",
    "town": "離",
    "town_kana": "ハナレ",
    "street": null,
    "office_name": null,
    "office_name_kana": null
  },
  "0103": {
    "postcode": "3740103",
    "prefecture": "群馬県",
    "prefecture_kana": "グンマケン",
    "prefecture_code": 10,
    "city": "邑楽郡板倉町",
    "city_kana": "オウラグンイタクラマチ",
    "town": "細谷",
    "town_kana": "ホソヤ",
    "street": null,
    "office_name": null,
    "office_name_kana": null
  },
  "0104": {
    "postcode": "3740104",
    "prefecture": "群馬県",
    "prefecture_kana": "グンマケン",
    "prefecture_code": 10,
    "city": "邑楽郡板倉町",
    "city_kana": "オウラグンイタクラマチ",
    "town": "大荷場",
    "town_kana": "オオニンバ",
    "street": null,
    "office_name": null,
    "office_name_kana": null
  },
  "0105": {
    "postcode": "3740105",
    "prefecture": "群馬県",
    "prefecture_kana": "グンマケン",
    "prefecture_code": 10,
    "city": "邑楽郡板倉町",
    "city_kana": "オウラグンイタクラマチ",
    "town": "大曲",
    "town_kana": "オオマガリ",
    "street": null,
    "office_name": null,
    "office_name_kana": null
  },
  "0106": {
    "postcode": "3740106",
    "prefecture": "群馬県",
    "prefecture_kana": "グンマケン",
    "prefecture_code": 10,
    "city": "邑楽郡板倉町",
    "city_kana": "オウラグンイタクラマチ",
    "town": "西岡新田",
    "town_kana": "ニシオカシンデン",
    "street": null,
    "office_name": null,
    "office_name_kana": null
  },
  "0107": {
    "postcode": "3740107",
    "prefecture": "群馬県",
    "prefecture_kana": "グンマケン",
    "prefecture_code": 10,
    "city": "邑楽郡板倉町",
    "city_kana": "オウラグンイタクラマチ",
    "town": "西岡",
    "town_kana": "ニシオカ",
    "street": null,
    "office_name": null,
    "office_name_kana": null
  },
  "0111": {
    "postcode": "3740111",
    "prefecture": "群馬県",
    "prefecture_kana": "グンマケン",
    "prefecture_code": 10,
    "city": "邑楽郡板倉町",
    "city_kana": "オウラグンイタクラマチ",
    "town": "海老瀬",
    "town_kana": "エビセ",
    "street": null,
    "office_name": null,
    "office_name_kana": null
  },
  "0112": {
    "postcode": "3740112",
    "prefecture": "群馬県",
    "prefecture_kana": "グンマケン",
    "prefecture_code": 10,
    "city": "邑楽郡板倉町",
    "city_kana": "オウラグンイタクラマチ",
    "town": "朝日野",
    "town_kana": "アサヒノ",
    "street": null,
    "office_name": null,
    "office_name_kana": null
  },
  "0113": {
    "postcode": "3740113",
    "prefecture": "群馬県",
    "prefecture_kana": "グンマケン",
    "prefecture_code": 10,
    "city": "邑楽郡板倉町",
    "city_kana": "オウラグンイタクラマチ",
    "town": "泉野",
    "town_kana": "イズミノ",
    "street": null,
    "office_name": null,
    "office_name_kana": null
  },
  "0121": {
    "postcode": "3740121",
    "prefecture": "群馬県",
    "prefecture_kana": "グンマケン",
    "prefecture_code": 10,
    "city": "邑楽郡板倉町",
    "city_kana": "オウラグンイタクラマチ",
    "town": "下五箇",
    "town_kana": "シモゴカ",
    "street": null,
    "office_name": null,
    "office_name_kana": null
  },
  "0122": {
    "postcode": "3740122",
    "prefecture": "群馬県",
    "prefecture_kana": "グンマケン",
    "prefecture_code": 10,
    "city": "邑楽郡板倉町",
    "city_kana": "オウラグンイタクラマチ",
    "town": "大高嶋",
    "town_kana": "オオタカシマ",
    "street": null,
    "office_name": null,
    "office_name_kana": null
  },
  "0123": {
    "postcode": "3740123",
    "prefecture": "群馬県",
    "prefecture_kana": "グンマケン",
    "prefecture_code": 10,
    "city": "邑楽郡板倉町",
    "city_kana": "オウラグンイタクラマチ",
    "town": "飯野",
    "town_kana": "イイノ",
    "street": null,
    "office_name": null,
    "office_name_kana": null
  },
  "0131": {
    "postcode": "3740131",
    "prefecture": "群馬県",
    "prefecture_kana": "グンマケン",
    "prefecture_code": 10,
    "city": "邑楽郡板倉町",
    "city_kana": "オウラグンイタクラマチ",
    "town": "大蔵",
    "town_kana": "オオクラ",
    "street": null,
    "office_name": null,
    "office_name_kana": null
  },
  "0132": {
    "postcode": "3740132",
    "prefecture": "群馬県",
    "prefecture_kana": "グンマケン",
    "prefecture_code": 10,
    "city": "邑楽郡板倉町",
    "city_kana": "オウラグンイタクラマチ",
    "town": "板倉",
    "town_kana": "イタクラ",
    "street": null,
    "office_name": null,
    "office_name_kana": null
  },
  "0133": {
    "postcode": "3740133",
    "prefecture": "群馬県",
    "prefecture_kana": "グンマケン",
    "prefecture_code": 10,
    "city": "邑楽郡板倉町",
    "city_kana": "オウラグンイタクラマチ",
    "town": "岩田",
    "town_kana": "イワタ",
    "street": null,
    "office_name": null,
    "office_name_kana": null
  },
  "0134": {
    "postcode": "3740134",
    "prefecture": "群馬県",
    "prefecture_kana": "グンマケン",
    "prefecture_code": 10,
    "city": "邑楽郡板倉町",
    "city_kana": "オウラグンイタクラマチ",
    "town": "籾谷",
    "town_kana": "モミヤ",
    "street": null,
    "office_name": null,
    "office_name_kana": null
  },
  "0135": {
    "postcode": "3740135",
    "prefecture": "群馬県",
    "prefecture_kana": "グンマケン",
    "prefecture_code": 10,
    "city": "邑楽郡板倉町",
    "city_kana": "オウラグンイタクラマチ",
    "town": "内蔵新田",
    "town_kana": "ウチクラシンデン",
    "street": null,
    "office_name": null,
    "office_name_kana": null
  },
  "0192": {
    "postcode": "3740192",
    "prefecture": "群馬県",
    "prefecture_kana": "グンマケン",
    "prefecture_code": 10,
    "city": "邑楽郡板倉町",
    "city_kana": "オウラグンイタクラマチ",
    "town": "大字板倉",
    "town_kana": null,
    "street": "２０６７",
    "office_name": "板倉町役場",
    "office_name_kana": "イタクラマチヤクバ"
  },
  "0193": {
    "postcode": "3740193",
    "prefecture": "群馬県",
    "prefecture_kana": "グンマケン",
    "prefecture_code": 10,
    "city": "邑楽郡板倉町",
    "city_kana": "オウラグンイタクラマチ",
    "town": "泉野",
    "town_kana": "イズミノ",
    "street": "１丁目１−１",
    "office_name": "東洋大学　板倉キャンパス",
    "office_name_kana": "トウヨウダイガク イタクラキヤンパス"
  },
  "8501": {
    "postcode": "3748501",
    "prefecture": "群馬県",
    "prefecture_kana": "グンマケン",
    "prefecture_code": 10,
    "city": "館林市",
    "city_kana": "タテバヤシシ",
    "town": "城町",
    "town_kana": "シロマチ",
    "street": "１−１",
    "office_name": "館林市役所",
    "office_name_kana": "タテバヤシシヤクシヨ"
  },
  "8510": {
    "postcode": "3748510",
    "prefecture": "群馬県",
    "prefecture_kana": "グンマケン",
    "prefecture_code": 10,
    "city": "館林市",
    "city_kana": "タテバヤシシ",
    "town": "栄町",
    "town_kana": "サカエチョウ",
    "street": "３−１",
    "office_name": "正田醤油　株式会社",
    "office_name_kana": "シヨウダシヨウユ カブシキガイシヤ"
  },
  "8511": {
    "postcode": "3748511",
    "prefecture": "群馬県",
    "prefecture_kana": "グンマケン",
    "prefecture_code": 10,
    "city": "館林市",
    "city_kana": "タテバヤシシ",
    "town": "近藤町",
    "town_kana": "コンドウチョウ",
    "street": "６６７番地",
    "office_name": "株式会社　アルティア橋本　館林工場",
    "office_name_kana": "(カブ) アルテイアハシモト タテバヤシコウジヨウ"
  },
  "8512": {
    "postcode": "3748512",
    "prefecture": "群馬県",
    "prefecture_kana": "グンマケン",
    "prefecture_code": 10,
    "city": "館林市",
    "city_kana": "タテバヤシシ",
    "town": "下早川田町",
    "town_kana": "シモサガワダチョウ",
    "street": "７００",
    "office_name": "株式会社　とりせん",
    "office_name_kana": "カブシキガイシヤ トリセン"
  },
  "8518": {
    "postcode": "3748518",
    "prefecture": "群馬県",
    "prefecture_kana": "グンマケン",
    "prefecture_code": 10,
    "city": "館林市",
    "city_kana": "タテバヤシシ",
    "town": "松原",
    "town_kana": "マツバラ",
    "street": "２丁目１９−６４",
    "office_name": "ニプロ医工　株式会社",
    "office_name_kana": "ニプロイコウ カブシキガイシヤ"
  },
  "8520": {
    "postcode": "3748520",
    "prefecture": "群馬県",
    "prefecture_kana": "グンマケン",
    "prefecture_code": 10,
    "city": "館林市",
    "city_kana": "タテバヤシシ",
    "town": "栄町",
    "town_kana": "サカエチョウ",
    "street": "１４−１",
    "office_name": "正田醤油株式会社　館林工場",
    "office_name_kana": "シヨウダシヨウユカブシキガイシヤ タテバヤシコウジヨウ"
  },
  "8533": {
    "postcode": "3748533",
    "prefecture": "群馬県",
    "prefecture_kana": "グンマケン",
    "prefecture_code": 10,
    "city": "館林市",
    "city_kana": "タテバヤシシ",
    "town": "成島町",
    "town_kana": "ナルシマチョウ",
    "street": "２６２−１",
    "office_name": "館林厚生病院",
    "office_name_kana": "タテバヤシコウセイビヨウイン"
  },
  "8555": {
    "postcode": "3748555",
    "prefecture": "群馬県",
    "prefecture_kana": "グンマケン",
    "prefecture_code": 10,
    "city": "館林市",
    "city_kana": "タテバヤシシ",
    "town": "大谷町",
    "town_kana": "オオヤチョウ",
    "street": "６２５",
    "office_name": "関東学園",
    "office_name_kana": "カントウガクエン"
  },
  "8577": {
    "postcode": "3748577",
    "prefecture": "群馬県",
    "prefecture_kana": "グンマケン",
    "prefecture_code": 10,
    "city": "館林市",
    "city_kana": "タテバヤシシ",
    "town": "近藤町",
    "town_kana": "コンドウチョウ",
    "street": "６４８",
    "office_name": "株式会社　アルファ　群馬工場",
    "office_name_kana": "カブシキガイシヤ アルフア グンマコウジヨウ"
  },
  "8588": {
    "postcode": "3748588",
    "prefecture": "群馬県",
    "prefecture_kana": "グンマケン",
    "prefecture_code": 10,
    "city": "館林市",
    "city_kana": "タテバヤシシ",
    "town": "本町",
    "town_kana": "ホンチョウ",
    "street": "３丁目８−１",
    "office_name": "株式会社　館林うどん",
    "office_name_kana": "カブシキガイシヤ タテバヤシウドン"
  },
  "8601": {
    "postcode": "3748601",
    "prefecture": "群馬県",
    "prefecture_kana": "グンマケン",
    "prefecture_code": 10,
    "city": "館林市",
    "city_kana": "タテバヤシシ",
    "town": "本町",
    "town_kana": "ホンチョウ",
    "street": "２丁目１０−８（館林郵便局私書箱第２０号）",
    "office_name": "群馬銀行　館林支店",
    "office_name_kana": "グンマギンコウ タテバヤシシテン"
  },
  "8608": {
    "postcode": "3748608",
    "prefecture": "群馬県",
    "prefecture_kana": "グンマケン",
    "prefecture_code": 10,
    "city": "館林市",
    "city_kana": "タテバヤシシ",
    "town": "本町",
    "town_kana": "ホンチョウ",
    "street": "１丁目６−３２（館林郵便局私書箱第２４号）",
    "office_name": "館林信用金庫",
    "office_name_kana": "タテバヤシシンヨウキンコ"
  },
  "8611": {
    "postcode": "3748611",
    "prefecture": "群馬県",
    "prefecture_kana": "グンマケン",
    "prefecture_code": 10,
    "city": "館林市",
    "city_kana": "タテバヤシシ",
    "town": "赤生田町",
    "town_kana": "アコウダチョウ",
    "street": "８４７",
    "office_name": "館林市農業協同組合",
    "office_name_kana": "タテバヤシシノウギヨウキヨウドウクミアイ"
  },
  "8622": {
    "postcode": "3748622",
    "prefecture": "群馬県",
    "prefecture_kana": "グンマケン",
    "prefecture_code": 10,
    "city": "館林市",
    "city_kana": "タテバヤシシ",
    "town": "大街道",
    "town_kana": "オオカイドウ",
    "street": "３丁目７−１（館林郵便局私書箱第１４号）",
    "office_name": "第一紙工　株式会社",
    "office_name_kana": "ダイイチシコウ カブシキガイシヤ"
  },
  "8640": {
    "postcode": "3748640",
    "prefecture": "群馬県",
    "prefecture_kana": "グンマケン",
    "prefecture_code": 10,
    "city": "館林市",
    "city_kana": "タテバヤシシ",
    "town": "大手町",
    "town_kana": "オオテマチ",
    "street": "１０−１（館林郵便局私書箱第１１号）",
    "office_name": "館林商工会議所",
    "office_name_kana": "タテバヤシシヨウコウカイギシヨ"
  },
  "8686": {
    "postcode": "3748686",
    "prefecture": "群馬県",
    "prefecture_kana": "グンマケン",
    "prefecture_code": 10,
    "city": "館林市",
    "city_kana": "タテバヤシシ",
    "town": "仲町",
    "town_kana": "ナカマチ",
    "street": "１１−１２（館林郵便局私書箱第１２号）",
    "office_name": "館林　税務署",
    "office_name_kana": "タテバヤシ ゼイムシヨ"
  }
}